boxen/__init__.py
boxen/boxen.py
boxen_python-0.1.3.dist-info/METADATA
boxen_python-0.1.3.dist-info/WHEEL
boxen_python-0.1.3.dist-info/licenses/LICENSE
boxen_python-0.1.3.dist-info/RECORD
