Metadata-Version: 2.4
Name: boxen-python
Version: 0.1.3
Summary: A simple, fast, dependencyless and intuitive library for creating boxes in the console 🎁
Project-URL: Homepage, https://github.com/itsmeadarsh2008/boxen
Project-URL: Repository, https://github.com/itsmeadarsh2008/boxen
Project-URL: Issues, https://github.com/itsmeadarsh2008/boxen/issues
Project-URL: Documentation, https://github.com/itsmeadarsh2008/boxen/blob/main/README.md
Author-email: Adarsh Gourab Mahalik <b6hkxu5od@mozmail.com>
License: MIT License
License-File: LICENSE
Keywords: boxes,cli,console,console-tools,console-ui,console-utilities,formatting,terminal,text
Classifier: Development Status :: 4 - Beta
Classifier: Intended Audience :: Developers
Classifier: License :: OSI Approved :: MIT License
Classifier: Operating System :: OS Independent
Classifier: Programming Language :: Python :: 3
Classifier: Programming Language :: Python :: 3.9
Classifier: Programming Language :: Python :: 3.10
Classifier: Programming Language :: Python :: 3.11
Classifier: Programming Language :: Python :: 3.12
Classifier: Topic :: Software Development :: User Interfaces
Classifier: Topic :: Terminals
Requires-Python: >=3.9
